flake8_assertive.py
flake8_assertive-2.2.0.dist-info/licenses/LICENSE
flake8_assertive-2.2.0.dist-info/METADATA
flake8_assertive-2.2.0.dist-info/WHEEL
flake8_assertive-2.2.0.dist-info/entry_points.txt
flake8_assertive-2.2.0.dist-info/top_level.txt
flake8_assertive-2.2.0.dist-info/zip-safe
flake8_assertive-2.2.0.dist-info/RECORD
