Metadata-Version: 2.4
Name: flake8-assertive
Version: 2.2.0
Summary: Flake8 unittest assert method checker
Home-page: https://github.com/jparise/flake8-assertive
Author: Jon Parise
Author-email: jon@indelible.org
License: MIT
Project-URL: Source Code, https://github.com/jparise/flake8-assertive
Project-URL: Issue Tracker, https://github.com/jparise/flake8-assertive/issues
Keywords: flake8 testing unittest assert
Classifier: Development Status :: 5 - Production/Stable
Classifier: Environment :: Console
Classifier: Framework :: Flake8
Classifier: Intended Audience :: Developers
Classifier: License :: OSI Approved :: MIT License
Classifier: Programming Language :: Python
Classifier: Programming Language :: Python :: 3 :: Only
Classifier: Programming Language :: Python :: 3.10
Classifier: Programming Language :: Python :: 3.11
Classifier: Programming Language :: Python :: 3.12
Classifier: Programming Language :: Python :: 3.13
Classifier: Programming Language :: Python :: 3.14
Classifier: Topic :: Software Development :: Libraries :: Python Modules
Classifier: Topic :: Software Development :: Quality Assurance
Classifier: Topic :: Software Development :: Testing
Classifier: Topic :: Software Development :: Testing :: Unit
Requires-Python: >=3.10
License-File: LICENSE
Requires-Dist: flake8>=3.0.0
Dynamic: license-file
Dynamic: requires-dist
